<?xml version="1.0" encoding="utf-8"?>
<ArrayOfTask1 xmlns:xsi="http://www.w3.org/2001/XMLSchema-instance" xmlns:xsd="http://www.w3.org/2001/XMLSchema">
  <Task1>
    <Id>1</Id>
    <Alias>T1</Alias>
    <Description>קניית מזון ומוצרים חד פעמיים</Description>
    <CreatedAtDate>2024-04-07T14:19:50</CreatedAtDate>
    <ScheduledDate>2024-04-07T14:19:50</ScheduledDate>
    <RequiredEffortTime>PT1H</RequiredEffortTime>
    <DeadlineDate>2024-04-07T15:19:50</DeadlineDate>
    <ChefId>781144067</ChefId>
    <StartDate>2024-04-07T14:19:50</StartDate>
    <CompleteDate>2024-04-07T16:19:50</CompleteDate>
    <Copmlexity>מתחיל</Copmlexity>
    <isMileStone xsi:nil="true" />
  </Task1>
  <Task1>
    <Id>2</Id>
    <Alias>T2</Alias>
    <Description>הכנת בצק</Description>
    <CreatedAtDate>2024-04-07T14:19:50</CreatedAtDate>
    <ScheduledDate>2024-04-07T15:19:50</ScheduledDate>
    <RequiredEffortTime>PT1H</RequiredEffortTime>
    <DeadlineDate>2024-04-07T16:19:50</DeadlineDate>
    <ChefId>0</ChefId>
    <StartDate xsi:nil="true" />
    <CompleteDate xsi:nil="true" />
    <Copmlexity>מתחיל</Copmlexity>
    <isMileStone>false</isMileStone>
  </Task1>
  <Task1>
    <Id>3</Id>
    <Alias>T3</Alias>
    <Description>שטיפה וקילוף ירקות</Description>
    <CreatedAtDate>2024-04-07T14:19:50</CreatedAtDate>
    <ScheduledDate>2024-04-07T15:19:50</ScheduledDate>
    <RequiredEffortTime>PT1H</RequiredEffortTime>
    <DeadlineDate>2024-04-07T16:19:50</DeadlineDate>
    <ChefId>781144067</ChefId>
    <StartDate xsi:nil="true" />
    <CompleteDate xsi:nil="true" />
    <Copmlexity>מתחיל</Copmlexity>
    <isMileStone>false</isMileStone>
  </Task1>
  <Task1>
    <Id>4</Id>
    <Alias>T4</Alias>
    <Description>אפיית הבצק ללחם</Description>
    <CreatedAtDate>2024-04-07T14:19:50</CreatedAtDate>
    <ScheduledDate>2024-04-07T16:19:50</ScheduledDate>
    <RequiredEffortTime>PT1H</RequiredEffortTime>
    <DeadlineDate>2024-04-07T17:19:50</DeadlineDate>
    <ChefId>0</ChefId>
    <StartDate xsi:nil="true" />
    <CompleteDate xsi:nil="true" />
    <Copmlexity>מתחיל</Copmlexity>
    <isMileStone>false</isMileStone>
  </Task1>
  <Task1>
    <Id>5</Id>
    <Alias>T5</Alias>
    <Description>חיתוך ירקות</Description>
    <CreatedAtDate>2024-04-07T14:19:50</CreatedAtDate>
    <ScheduledDate>2024-04-07T16:19:50</ScheduledDate>
    <RequiredEffortTime>PT1H</RequiredEffortTime>
    <DeadlineDate>2024-04-07T17:19:50</DeadlineDate>
    <ChefId>0</ChefId>
    <StartDate xsi:nil="true" />
    <CompleteDate xsi:nil="true" />
    <Copmlexity>מתחיל</Copmlexity>
    <isMileStone>false</isMileStone>
  </Task1>
  <Task1>
    <Id>6</Id>
    <Alias>T6</Alias>
    <Description>הכנת סלטים</Description>
    <CreatedAtDate>2024-04-07T14:19:50</CreatedAtDate>
    <ScheduledDate>2024-04-07T17:19:50</ScheduledDate>
    <RequiredEffortTime>PT1H</RequiredEffortTime>
    <DeadlineDate>2024-04-07T18:19:50</DeadlineDate>
    <ChefId>0</ChefId>
    <StartDate xsi:nil="true" />
    <CompleteDate xsi:nil="true" />
    <Copmlexity>מתחיל</Copmlexity>
    <isMileStone>false</isMileStone>
  </Task1>
  <Task1>
    <Id>7</Id>
    <Alias>T7</Alias>
    <Description>בישול מרק</Description>
    <CreatedAtDate>2024-04-07T14:19:50</CreatedAtDate>
    <ScheduledDate>2024-04-07T18:19:50</ScheduledDate>
    <RequiredEffortTime>PT1H</RequiredEffortTime>
    <DeadlineDate>2024-04-07T19:19:50</DeadlineDate>
    <ChefId>0</ChefId>
    <StartDate xsi:nil="true" />
    <CompleteDate xsi:nil="true" />
    <Copmlexity>מתחיל</Copmlexity>
    <isMileStone>false</isMileStone>
  </Task1>
  <Task1>
    <Id>8</Id>
    <Alias>T8</Alias>
    <Description>אפיית דגים</Description>
    <CreatedAtDate>2024-04-07T14:19:50</CreatedAtDate>
    <ScheduledDate>2024-04-07T18:19:50</ScheduledDate>
    <RequiredEffortTime>PT1H</RequiredEffortTime>
    <DeadlineDate>2024-04-07T19:19:50</DeadlineDate>
    <ChefId>0</ChefId>
    <StartDate xsi:nil="true" />
    <CompleteDate xsi:nil="true" />
    <Copmlexity>מתחיל</Copmlexity>
    <isMileStone>false</isMileStone>
  </Task1>
  <Task1>
    <Id>9</Id>
    <Alias>T9</Alias>
    <Description>הכנת בשר</Description>
    <CreatedAtDate>2024-04-07T14:19:50</CreatedAtDate>
    <ScheduledDate>2024-04-07T19:19:50</ScheduledDate>
    <RequiredEffortTime>PT1H</RequiredEffortTime>
    <DeadlineDate>2024-04-07T20:19:50</DeadlineDate>
    <ChefId>0</ChefId>
    <StartDate xsi:nil="true" />
    <CompleteDate xsi:nil="true" />
    <Copmlexity>מתחיל</Copmlexity>
    <isMileStone>false</isMileStone>
  </Task1>
  <Task1>
    <Id>10</Id>
    <Alias>T10</Alias>
    <Description>הכנת תוספת לבשר</Description>
    <CreatedAtDate>2024-04-07T14:19:50</CreatedAtDate>
    <ScheduledDate>2024-04-07T19:19:50</ScheduledDate>
    <RequiredEffortTime>PT1H</RequiredEffortTime>
    <DeadlineDate>2024-04-07T20:19:50</DeadlineDate>
    <ChefId>0</ChefId>
    <StartDate xsi:nil="true" />
    <CompleteDate xsi:nil="true" />
    <Copmlexity>מתחיל</Copmlexity>
    <isMileStone>false</isMileStone>
  </Task1>
  <Task1>
    <Id>11</Id>
    <Alias>T11</Alias>
    <Description>הכנת קינוח</Description>
    <CreatedAtDate>2024-04-07T14:19:50</CreatedAtDate>
    <ScheduledDate>2024-04-07T20:19:50</ScheduledDate>
    <RequiredEffortTime>PT1H</RequiredEffortTime>
    <DeadlineDate>2024-04-07T21:19:50</DeadlineDate>
    <ChefId>0</ChefId>
    <StartDate xsi:nil="true" />
    <CompleteDate xsi:nil="true" />
    <Copmlexity>מתחיל</Copmlexity>
    <isMileStone>false</isMileStone>
  </Task1>
  <Task1>
    <Id>12</Id>
    <Alias>T12</Alias>
    <Description>ניקוי מטבח</Description>
    <CreatedAtDate>2024-04-07T14:19:50</CreatedAtDate>
    <ScheduledDate>2024-04-07T21:19:50</ScheduledDate>
    <RequiredEffortTime>PT1H</RequiredEffortTime>
    <DeadlineDate>2024-04-07T22:19:50</DeadlineDate>
    <ChefId>0</ChefId>
    <StartDate xsi:nil="true" />
    <CompleteDate xsi:nil="true" />
    <Copmlexity>מתחיל</Copmlexity>
    <isMileStone>false</isMileStone>
  </Task1>
  <Task1>
    <Id>13</Id>
    <Alias>T13</Alias>
    <Description>בחירת כלי הגשה</Description>
    <CreatedAtDate>2024-04-07T14:19:50</CreatedAtDate>
    <ScheduledDate>2024-04-07T22:19:50</ScheduledDate>
    <RequiredEffortTime>PT1H</RequiredEffortTime>
    <DeadlineDate>2024-04-07T23:19:50</DeadlineDate>
    <ChefId>0</ChefId>
    <StartDate xsi:nil="true" />
    <CompleteDate xsi:nil="true" />
    <Copmlexity>מתחיל</Copmlexity>
    <isMileStone>false</isMileStone>
  </Task1>
  <Task1>
    <Id>14</Id>
    <Alias>T14</Alias>
    <Description>עיצוב קינוח</Description>
    <CreatedAtDate>2024-04-07T14:19:50</CreatedAtDate>
    <ScheduledDate>2024-04-07T22:19:50</ScheduledDate>
    <RequiredEffortTime>PT1H</RequiredEffortTime>
    <DeadlineDate>2024-04-07T23:19:50</DeadlineDate>
    <ChefId>0</ChefId>
    <StartDate xsi:nil="true" />
    <CompleteDate xsi:nil="true" />
    <Copmlexity>מתחיל</Copmlexity>
    <isMileStone>false</isMileStone>
  </Task1>
  <Task1>
    <Id>15</Id>
    <Alias>T15</Alias>
    <Description>עיצוב שולחן</Description>
    <CreatedAtDate>2024-04-07T14:19:50</CreatedAtDate>
    <ScheduledDate>2024-04-07T23:19:50</ScheduledDate>
    <RequiredEffortTime>PT1H</RequiredEffortTime>
    <DeadlineDate>2024-04-08T00:19:50</DeadlineDate>
    <ChefId>0</ChefId>
    <StartDate xsi:nil="true" />
    <CompleteDate xsi:nil="true" />
    <Copmlexity>מתחיל</Copmlexity>
    <isMileStone>false</isMileStone>
  </Task1>
  <Task1>
    <Id>16</Id>
    <Alias>T16</Alias>
    <Description>סידור הכסאות</Description>
    <CreatedAtDate>2024-04-07T14:19:50</CreatedAtDate>
    <ScheduledDate>2024-04-07T23:19:50</ScheduledDate>
    <RequiredEffortTime>PT1H</RequiredEffortTime>
    <DeadlineDate>2024-04-08T00:19:50</DeadlineDate>
    <ChefId>0</ChefId>
    <StartDate xsi:nil="true" />
    <CompleteDate xsi:nil="true" />
    <Copmlexity>מתחיל</Copmlexity>
    <isMileStone>false</isMileStone>
  </Task1>
  <Task1>
    <Id>17</Id>
    <Alias>T17</Alias>
    <Description>הגשת משקאות</Description>
    <CreatedAtDate>2024-04-07T14:19:50</CreatedAtDate>
    <ScheduledDate>2024-04-08T00:19:50</ScheduledDate>
    <RequiredEffortTime>PT1H</RequiredEffortTime>
    <DeadlineDate>2024-04-08T01:19:50</DeadlineDate>
    <ChefId>0</ChefId>
    <StartDate xsi:nil="true" />
    <CompleteDate xsi:nil="true" />
    <Copmlexity>מתחיל</Copmlexity>
    <isMileStone>false</isMileStone>
  </Task1>
  <Task1>
    <Id>18</Id>
    <Alias>T18</Alias>
    <Description>פינוי השולחן</Description>
    <CreatedAtDate>2024-04-07T14:19:50</CreatedAtDate>
    <ScheduledDate>2024-04-08T00:19:50</ScheduledDate>
    <RequiredEffortTime>PT1H</RequiredEffortTime>
    <DeadlineDate>2024-04-08T01:19:50</DeadlineDate>
    <ChefId>0</ChefId>
    <StartDate xsi:nil="true" />
    <CompleteDate xsi:nil="true" />
    <Copmlexity>מתחיל</Copmlexity>
    <isMileStone>false</isMileStone>
  </Task1>
  <Task1>
    <Id>19</Id>
    <Alias>T19</Alias>
    <Description>סדר וניקיון המקום</Description>
    <CreatedAtDate>2024-04-07T14:19:50</CreatedAtDate>
    <ScheduledDate>2024-04-08T01:19:50</ScheduledDate>
    <RequiredEffortTime>PT1H</RequiredEffortTime>
    <DeadlineDate>2024-04-08T02:19:50</DeadlineDate>
    <ChefId>0</ChefId>
    <StartDate xsi:nil="true" />
    <CompleteDate xsi:nil="true" />
    <Copmlexity>מתחיל</Copmlexity>
    <isMileStone>false</isMileStone>
  </Task1>
</ArrayOfTask1>